setup.py
distributions/Binomialdistribution.py
distributions/Gaussiandistribution.py
distributions/Generaldistribution.py
distributions/__init__.py
distributionss.egg-info/PKG-INFO
distributionss.egg-info/SOURCES.txt
distributionss.egg-info/dependency_links.txt
distributionss.egg-info/not-zip-safe
distributionss.egg-info/top_level.txt